analysis/__init__.py
analysis/bsfc_profile_plot.py
analysis/bsfc_synthetic_generator.py
analysis/bsfc_synthetic_profile_plot.py
analysis/bsfc_test_synthetic.py
bsfc/__init__.py
bsfc/bsfc_bin_fit.py
bsfc/bsfc_line_model.py
bsfc/bsfc_moment_fitter.py
bsfc/bsfc_profiles.py
bsfc/bsfc_read_nhermite_scan.py
bsfc/bsfc_run.py
bsfc/bsfc_run_mpi.py
bsfc/bsfc_run_ns.py
bsfc/bsfc_run_profile.py
bsfc/bsfc_run_synth_ns.py
bsfc/bsfc_run_synth_profile.py
bsfc/bsfc_scan_nhermite.py
bsfc/launch_NSfit.py
helpers/__init__.py
helpers/bsfc_autocorr.py
helpers/bsfc_clean_moments.py
helpers/bsfc_cmod_shots.py
helpers/bsfc_get_moments.py
helpers/bsfc_helper.py
helpers/bsfc_prior_bound_calculator.py
helpers/bsfc_prior_bound_calculator_debug.py
helpers/bsfc_slider.py
helpers/save_bsfc4mitim.py
helpers/simplex_sampling.py
syn_tests/__init__.py
syn_tests/bsfc_synthetic_profile_plot.py
syn_tests/bsfc_synthetic_profile_test.py
syn_tests/bsfc_test_numcoefs.py
syn_tests/bsfc_test_synthetic.py
bsfc-1.0.1.dist-info/LICENSE
bsfc-1.0.1.dist-info/METADATA
bsfc-1.0.1.dist-info/WHEEL
bsfc-1.0.1.dist-info/top_level.txt
bsfc-1.0.1.dist-info/RECORD
