Metadata-Version: 2.1
Name: bsfc
Version: 1.0.1
Summary: Bayesian Spectral Fitting Code (BSFC)
Home-page: https://github.com/Maplenormandy/bsfc
Author: Francesco Sciortino and Norman Cao
Author-email: sciortino@psfc.mit.edu
Maintainer: Francesco Sciortino
Maintainer-email: sciortino@psfc.mit.edu
License: UNKNOWN
Platform: UNKNOWN
Classifier: Programming Language :: Python :: 2.7
Classifier: License :: OSI Approved :: MIT License
Classifier: Operating System :: OS Independent
